tinybgw/__init__.py
tinybgw/bits.py
tinybgw/combinations.py
tinybgw/lagrange.py
tinybgw/lessthan.py
tinybgw/network.py
tinybgw/node.py
tinybgw/prefix.py
tinybgw/pseudo_network.py
tinybgw/pseudo_node.py
tinybgw/shamir.py
tinybgw/sharer.py
tinybgw/trunc.py
tinybgw-0.1.0.dist-info/LICENSE
tinybgw-0.1.0.dist-info/METADATA
tinybgw-0.1.0.dist-info/WHEEL
tinybgw-0.1.0.dist-info/top_level.txt
tinybgw-0.1.0.dist-info/RECORD
