Metadata-Version: 2.1
Name: tinybgw
Version: 0.1.0
Summary: Pure-Python implementation of a threshold secure multi-party computation (MPC) network.
Author: Nillion
Author-email: engineering@nillion.com
License: MIT
Project-URL: Repository, https://github.com/nillion-oss/tinybgw
Project-URL: Documentation, https://tinybgw.readthedocs.io
Requires-Python: >=3.10
License-File: LICENSE
Requires-Dist: gmpy2 ~=2.1.5
Requires-Dist: llvmlite ~=0.41.1
Requires-Dist: mpmath ~=1.3.0
Requires-Dist: numba ~=0.58.1
Requires-Dist: numpy ~=1.25.2
Requires-Dist: phe ~=1.5.0
Requires-Dist: pycryptodome ~=3.19.0
Requires-Dist: sympy ~=1.12
Requires-Dist: typing-extensions ~=4.8.0
Provides-Extra: coveralls
Requires-Dist: coveralls ~=3.3.1 ; extra == 'coveralls'
Provides-Extra: docs
Requires-Dist: toml ~=0.10.2 ; extra == 'docs'
Requires-Dist: sphinx ~=4.2.0 ; extra == 'docs'
Requires-Dist: sphinx-rtd-theme ~=1.0.0 ; extra == 'docs'
Requires-Dist: sphinx-autodoc-typehints ~=1.12.0 ; extra == 'docs'
Provides-Extra: lint
Requires-Dist: pylint ~=2.17.0 ; extra == 'lint'
Provides-Extra: publish
Requires-Dist: build ~=0.10 ; extra == 'publish'
Requires-Dist: twine ~=4.0 ; extra == 'publish'
Provides-Extra: test
Requires-Dist: pytest ~=7.2 ; extra == 'test'
Requires-Dist: pytest-cov ~=4.0 ; extra == 'test'
